scripts/__init__.py
scripts/singleston.py
scripts/version.py
singleston-1.0.2.dist-info/licenses/LICENSE
tests/__init__.py
tests/test_command_line.py
tests/test_dependency_parser.py
tests/test_error_handling.py
tests/test_export.py
tests/test_file_processor.py
tests/test_include_guard_removal.py
tests/test_utils.py
tests/fixtures/edge_cases/include_guards/nested_conditionals.hpp
tests/fixtures/edge_cases/include_guards/pragma_once.hpp
tests/fixtures/edge_cases/include_guards/traditional_guard.h
tests/fixtures/expected_outputs/simple_project_output.cpp
tests/fixtures/simple_project/include/utils.hpp
tests/fixtures/simple_project/srcs/main.cpp
tests/fixtures/simple_project/srcs/utils.cpp
singleston-1.0.2.dist-info/METADATA
singleston-1.0.2.dist-info/WHEEL
singleston-1.0.2.dist-info/entry_points.txt
singleston-1.0.2.dist-info/top_level.txt
singleston-1.0.2.dist-info/RECORD
