Metadata-Version: 2.4
Name: singleston
Version: 1.0.2
Summary: A powerful source file amalgamator for C/C++ projects
Author-email: Adrien Soursou <adrien.soursou@gmail.com>
License-Expression: MIT
Project-URL: Homepage, https://github.com/ChuOkupai/singleston
Project-URL: Bug Reports, https://github.com/ChuOkupai/singleston/issues
Project-URL: Source, https://github.com/ChuOkupai/singleston
Classifier: Development Status :: 4 - Beta
Classifier: Intended Audience :: Developers
Classifier: Operating System :: OS Independent
Classifier: Programming Language :: Python :: 3
Classifier: Programming Language :: Python :: 3.9
Classifier: Programming Language :: Python :: 3.10
Classifier: Programming Language :: Python :: 3.11
Classifier: Programming Language :: Python :: 3.12
Classifier: Programming Language :: Python :: 3.13
Classifier: Topic :: Software Development :: Build Tools
Classifier: Topic :: Software Development :: Code Generators
Requires-Python: >=3.9
License-File: LICENSE
Dynamic: license-file
